squelch/__init__.py
squelch/__main__.py
squelch-0.5.0.dist-info/entry_points.txt
squelch-0.5.0.dist-info/LICENSE
squelch-0.5.0.dist-info/WHEEL
squelch-0.5.0.dist-info/METADATA
squelch-0.5.0.dist-info/RECORD
