Metadata-Version: 2.1
Name: squelch
Version: 0.5.0
Summary: Simple SQL REPL Command Handler
Home-page: https://github.com/paul-breen/squelch
License: Apache-2.0
Author: Paul Breen
Author-email: pbree@bas.ac.uk
Requires-Python: >=3.8,<4.0
Classifier: License :: OSI Approved :: Apache Software License
Classifier: Programming Language :: Python :: 3
Classifier: Programming Language :: Python :: 3.8
Classifier: Programming Language :: Python :: 3.9
Classifier: Programming Language :: Python :: 3.10
Classifier: Programming Language :: Python :: 3.11
Requires-Dist: sqlalchemy (>=2.0.29,<3.0.0)
Requires-Dist: tabulate (>=0.9.0,<0.10.0)
Project-URL: Documentation, https://paul-breen.github.io/squelch/
Project-URL: Repository, https://github.com/paul-breen/squelch
